odoo/addons/account_mail_autosubscribe/README.rst
odoo/addons/account_mail_autosubscribe/__init__.py
odoo/addons/account_mail_autosubscribe/__manifest__.py
odoo/addons/account_mail_autosubscribe/data/mail_autosubscribe.xml
odoo/addons/account_mail_autosubscribe/i18n/account_mail_autosubscribe.pot
odoo/addons/account_mail_autosubscribe/i18n/fr.po
odoo/addons/account_mail_autosubscribe/i18n/it.po
odoo/addons/account_mail_autosubscribe/readme/CONFIGURE.rst
odoo/addons/account_mail_autosubscribe/readme/CONTRIBUTORS.rst
odoo/addons/account_mail_autosubscribe/readme/DESCRIPTION.rst
odoo/addons/account_mail_autosubscribe/static/description/icon.png
odoo/addons/account_mail_autosubscribe/static/description/index.html
odoo14_addon_account_mail_autosubscribe-14.0.1.0.1.dev6.dist-info/METADATA
odoo14_addon_account_mail_autosubscribe-14.0.1.0.1.dev6.dist-info/WHEEL
odoo14_addon_account_mail_autosubscribe-14.0.1.0.1.dev6.dist-info/top_level.txt
odoo14_addon_account_mail_autosubscribe-14.0.1.0.1.dev6.dist-info/RECORD
